KratosMultiphysics/StemApplication/__init__.py
KratosMultiphysics/StemApplication/geomechanics_U_Pw_solver.py
KratosMultiphysics/StemApplication/geomechanics_analysis.py
KratosMultiphysics/StemApplication/geomechanics_newton_raphson_strategy.py
KratosMultiphysics/StemApplication/geomechanics_solvers_wrapper.py
KratosMultiphysics/StemApplication/run_multiple_stages.py
KratosMultiphysics/StemApplication/set_moving_load_process.py
KratosMultiphysics/StemApplication/set_multiple_moving_loads_process.py
KratosMultiphysics/StemApplication/set_nodal_parameters_process.py
KratosMultiphysics/StemApplication/set_parameter_field_process.py
KratosMultiphysics/StemApplication/uvec_controller.py
StemKratos/__init__.py
StemKratos/__version__.py
StemKratos-1.2.0.1.dist-info/METADATA
StemKratos-1.2.0.1.dist-info/WHEEL
StemKratos-1.2.0.1.dist-info/dependency_links.txt
StemKratos-1.2.0.1.dist-info/top_level.txt
StemKratos-1.2.0.1.dist-info/RECORD
